aioraven/__init__.py
aioraven/data.py
aioraven/device.py
aioraven/protocols.py
aioraven/py.typed
aioraven/reader.py
aioraven/serial.py
aioraven/streams.py
aioraven-0.7.0.dist-info/LICENSE
aioraven-0.7.0.dist-info/METADATA
aioraven-0.7.0.dist-info/WHEEL
aioraven-0.7.0.dist-info/top_level.txt
aioraven-0.7.0.dist-info/RECORD
